plumai/__init__.py
plumai/app.py
plumai/plumai.py
plumai/models/__init__.py
plumai/models/flux1_dev.py
plumai/models/flux1_schnell.py
plumai/templates/index.html
plumai-0.1.13.dist-info/LICENSE
plumai-0.1.13.dist-info/METADATA
plumai-0.1.13.dist-info/WHEEL
plumai-0.1.13.dist-info/entry_points.txt
plumai-0.1.13.dist-info/top_level.txt
plumai-0.1.13.dist-info/RECORD
