Metadata-Version: 2.1
Name: plumai
Version: 0.1.13
Summary: A tool for deploying and running AI models to Modal
Author-email: Tam Nguyen <tamnvhustcc@gmail.com>
Project-URL: Homepage, https://x.com/tamnvvn
Classifier: License :: OSI Approved :: MIT License
Classifier: Programming Language :: Python :: 3
Classifier: Programming Language :: Python :: 3.8
Classifier: Programming Language :: Python :: 3.9
Classifier: Programming Language :: Python :: 3.10
Classifier: Programming Language :: Python :: 3.11
Classifier: Programming Language :: Python :: 3.12
Requires-Python: >=3.8
License-File: LICENSE
Requires-Dist: Flask<=3.0.3,>=2.0.0
Requires-Dist: modal<=0.64.16,>=0.64.0
Requires-Dist: requests>2.9.0
Requires-Dist: colorama>0.4.0
